cdkeks/__init__.py
cdkeks/py.typed
cdkeks/_jsii/__init__.py
cdkeks/_jsii/cdkeks@0.0.4.jsii.tgz
cdkeks-0.0.4.dist-info/LICENSE
cdkeks-0.0.4.dist-info/METADATA
cdkeks-0.0.4.dist-info/WHEEL
cdkeks-0.0.4.dist-info/top_level.txt
cdkeks-0.0.4.dist-info/RECORD
