Metadata-Version: 2.1
Name: cdkeks
Version: 0.0.4
Summary: Higher-level hybrid cdk|cdk8s construct to build an eks kubernetes platform with batteries included
Home-page: https://github.com/hupe1980/cdkeks
Author: hupe1980
License: MIT
Project-URL: Source, https://github.com/hupe1980/cdkeks.git
Platform: UNKNOWN
Classifier: Intended Audience :: Developers
Classifier: Operating System :: OS Independent
Classifier: Programming Language :: JavaScript
Classifier: Programming Language :: Python :: 3 :: Only
Classifier: Programming Language :: Python :: 3.6
Classifier: Programming Language :: Python :: 3.7
Classifier: Programming Language :: Python :: 3.8
Classifier: Programming Language :: Python :: 3.9
Classifier: Typing :: Typed
Classifier: License :: OSI Approved
Requires-Python: >=3.6
Requires-Dist: aws-cdk.aws-certificatemanager (<2.0.0,>=1.107.0)
Requires-Dist: aws-cdk.aws-ec2 (<2.0.0,>=1.107.0)
Requires-Dist: aws-cdk.aws-efs (<2.0.0,>=1.107.0)
Requires-Dist: aws-cdk.aws-eks (<2.0.0,>=1.107.0)
Requires-Dist: aws-cdk.aws-elasticloadbalancingv2 (<2.0.0,>=1.107.0)
Requires-Dist: aws-cdk.aws-elasticsearch (<2.0.0,>=1.107.0)
Requires-Dist: aws-cdk.aws-iam (<2.0.0,>=1.107.0)
Requires-Dist: aws-cdk.aws-logs (<2.0.0,>=1.107.0)
Requires-Dist: aws-cdk.aws-route53 (<2.0.0,>=1.107.0)
Requires-Dist: aws-cdk.aws-s3 (<2.0.0,>=1.107.0)
Requires-Dist: aws-cdk.core (<2.0.0,>=1.107.0)
Requires-Dist: cdk8s-plus-17 (<2.0.0,>=1.0.0.b20)
Requires-Dist: cdk8s (==1.0.0.b14)
Requires-Dist: constructs (<4.0.0,>=3.3.75)
Requires-Dist: jsii (<2.0.0,>=1.30.0)
Requires-Dist: publication (>=0.0.3)
